[
    {
        "name": "Hockey",
        "discription": "Discription",
        "discri": "A fast-paced team sport played on an ice rink (ice hockey) or a field (field hockey) where players use sticks to hit a puck or ball into the opponent's goal, promoting teamwork, strategy, and athleticism. Perfect for bringing excitement and competitive spirit to any gathering.",
        "pack": "Package includes...",
        "minTime": "Minimum of 3 hours of play.",
        "maxTime":"This exciting kids party will give your child a birthday of memories and fun picnic games for just",
        "price": "8000",
        "midTime": " per game per hour",
        "newURL": "../images/card-team-8.jpg"
    }
]